statsd/__init__.py
statsd/client.py
statsd/formats.py
statsd/py.typed
statsd/version.py
statsd_python-0.6.1.dist-info/LICENSE
statsd_python-0.6.1.dist-info/METADATA
statsd_python-0.6.1.dist-info/WHEEL
statsd_python-0.6.1.dist-info/top_level.txt
statsd_python-0.6.1.dist-info/RECORD
