Metadata-Version: 2.1
Name: statsd-python
Version: 0.6.1
Home-page: https://github.com/lirsacc/statsd_client_python
Author: Charles Lirsac
Author-email: c.lirsac@gmail.com
License: MIT
Project-URL: Bug Reports, https://github.com/lirsacc/statsd_client_python/issues
Project-URL: Source, https://github.com/lirsacc/statsd_client_python
Keywords: statsd metrics
Classifier: Development Status :: 4 - Beta
Classifier: Intended Audience :: Developers
Classifier: Natural Language :: English
Classifier: License :: OSI Approved :: MIT License
Classifier: Operating System :: OS Independent
Classifier: Programming Language :: Python
Classifier: Programming Language :: Python :: 3 :: Only
Classifier: Programming Language :: Python :: 3.7
Classifier: Programming Language :: Python :: 3.8
Classifier: Programming Language :: Python :: 3.9
Classifier: Programming Language :: Python :: 3.10
Classifier: Programming Language :: Python :: 3.11
Classifier: Typing :: Typed
Classifier: Topic :: Software Development :: Libraries
Classifier: Topic :: Software Development :: Libraries :: Python Modules
Requires-Python: >=3.6
License-File: LICENSE
